antoine_dragonfly-0.3.1.dist-info/DESCRIPTION.rst
antoine_dragonfly-0.3.1.dist-info/METADATA
antoine_dragonfly-0.3.1.dist-info/RECORD
antoine_dragonfly-0.3.1.dist-info/WHEEL
antoine_dragonfly-0.3.1.dist-info/dependency_links.txt
antoine_dragonfly-0.3.1.dist-info/entry_points.txt
antoine_dragonfly-0.3.1.dist-info/metadata.json
antoine_dragonfly-0.3.1.dist-info/top_level.txt
dragonfly/__init__.py
dragonfly/bldgtypes.py
dragonfly/city.py
dragonfly/dfobject.py
dragonfly/dfparameter.py
dragonfly/terrain.py
dragonfly/typology.py
dragonfly/utilities.py
dragonfly/vegetation.py
dragonfly/resources/readDOE.pkl
