Metadata-Version: 2.0
Name: antoine-dragonfly
Version: 0.3.1
Summary: Dragonfly is a utility API to work with UWG
Home-page: https://github.com/ladybug-tools/dragonfly
Author: ladybug-tools
Author-email: UNKNOWN
License: UNKNOWN
Platform: UNKNOWN
Classifier: Programming Language :: Python :: 2.7
Classifier: Operating System :: OS Independent
